fir_filter.v
module fir_filter #(
    parameter TAPS = 4
)(
    input  wire               clk,
    input  wire               rst,
    input  wire signed [15:0] sample_in,
    input  wire               sample_valid,
    output reg  signed [15:0] y_out
);

    reg signed [15:0] shift_reg [0:TAPS-1];
    reg signed [15:0] coeff     [0:TAPS-1];
    reg signed [31:0] acc;
    integer i;

    initial begin
        for (i = 0; i < TAPS; i = i + 1)
            coeff[i] = 16'sh2000; // 0.25 in Q1.15
    end

    always @(posedge clk) begin
        if (rst) begin
            for (i = 0; i < TAPS; i = i + 1)
                shift_reg[i] <= 16'sd0;
            y_out <= 16'sd0;
        end else if (sample_valid) begin

            for (i = TAPS-1; i > 0; i = i - 1)
                shift_reg[i] <= shift_reg[i-1];

            shift_reg[0] <= sample_in;

            acc = 32'sd0;
            for (i = 0; i < TAPS; i = i + 1)
                acc = acc + (shift_reg[i] * coeff[i]);

            y_out <= acc[30:15];
        end
    end

endmodule

tb_fir_filter.v
`timescale 1ns/1ps

module tb_fir_filter;

    reg clk;
    reg rst;
    reg signed [15:0] sample_in;
    reg sample_valid;
    wire signed [15:0] y_out;

    fir_filter #(.TAPS(4)) dut (
        .clk(clk),
        .rst(rst),
        .sample_in(sample_in),
        .sample_valid(sample_valid),
        .y_out(y_out)
    );

    always #5 clk = ~clk;

    initial begin
        $dumpfile("dump.vcd");
        $dumpvars(0, tb_fir_filter);

        clk = 0;
        rst = 1;
        sample_in = 0;
        sample_valid = 0;

        #20;
        rst = 0;

        // Impulse
        #10;
        sample_valid = 1;
        sample_in = 16'sh7FFF;

        #10 sample_in = 16'sd0;
        #10 sample_in = 16'sd0;
        #10 sample_in = 16'sd0;

        #10 sample_valid = 0;

        #50;

        // Step
        sample_valid = 1;
        sample_in = 16'sh4000;

        #10 sample_in = 16'sh4000;
        #10 sample_in = 16'sh4000;
        #10 sample_in = 16'sh4000;

        #10 sample_valid = 0;

        #50;
        $stop;
    end

endmodule

dump.vcd
$date
	Fri Jan 16 18:52:43 2026
$end
$version
	Icarus Verilog
$end
$timescale
	1ps
$end
$scope module tb_fir_filter $end
$var wire 16 ! y_out [15:0] $end
$var reg 1 " clk $end
$var reg 1 # rst $end
$var reg 16 $ sample_in [15:0] $end
$var reg 1 % sample_valid $end
$scope module dut $end
$var wire 1 " clk $end
$var wire 1 # rst $end
$var wire 16 & sample_in [15:0] $end
$var wire 1 % sample_valid $end
$var parameter 32 ' TAPS $end
$var reg 32 ( acc [31:0] $end
$var reg 16 ) y_out [15:0] $end
$var integer 32 * i [31:0] $end
$upscope $end
$upscope $end
$enddefinitions $end
$comment Show the parameter values. $end
$dumpall
b100 '
$end
#0
$dumpvars
b100 *
bx )
bx (
b0 &
0%
b0 $
1#
0"
bx !
$end
#5000
b0 !
b0 )
b100 *
1"
#10000
0"
#15000
b100 *
1"
#20000
0"
0#
#25000
1"
#30000
0"
b111111111111111 $
b111111111111111 &
1%
#35000
b0 (
b100 *
1"
#40000
0"
b0 $
b0 &
#45000
b1111111111111 !
b1111111111111 )
b1111111111111110000000000000 (
b100 *
1"
#50000
0"
#55000
b1111111111111110000000000000 (
b100 *
1"
#60000
0"
#65000
b1111111111111110000000000000 (
b100 *
1"
#70000
0"
0%
#75000
1"
#80000
0"
#85000
1"
#90000
0"
#95000
1"
#100000
0"
#105000
1"
#110000
0"
#115000
1"
#120000
0"
b100000000000000 $
b100000000000000 &
1%
#125000
b1111111111111110000000000000 (
b100 *
1"
#130000
0"
#135000
b1000000000000 !
b1000000000000 )
b1000000000000000000000000000 (
b100 *
1"
#140000
0"
#145000
b10000000000000 !
b10000000000000 )
b10000000000000000000000000000 (
b100 *
1"
#150000
0"
#155000
b11000000000000 !
b11000000000000 )
b11000000000000000000000000000 (
b100 *
1"
#160000
0"
0%
